cuitonline.py
cuitonline-0.1.1.dist-info/entry_points.txt
cuitonline-0.1.1.dist-info/WHEEL
cuitonline-0.1.1.dist-info/METADATA
cuitonline-0.1.1.dist-info/RECORD
