Metadata-Version: 2.3
Name: cuitonline
Version: 0.1.1
Summary: CLI y biblioteca Python de cuitonline.com. No oficial.
Author-email: Martín Gaitán <gaitan@gmail.com>
Requires-Python: >=3.12
Requires-Dist: beautifulsoup4>=4.12
Requires-Dist: pydantic>=2.10
Requires-Dist: requests
Project-URL: Home, https://github.com/mgaitan/cuitonline
